yjf_mcp/__init__.py
yjf_mcp/user_location.py
yjf_mcp-0.1.0.dist-info/WHEEL
yjf_mcp-0.1.0.dist-info/entry_points.txt
yjf_mcp-0.1.0.dist-info/METADATA
yjf_mcp-0.1.0.dist-info/RECORD
