Metadata-Version: 2.3
Name: yjf-mcp
Version: 0.1.0
Summary: Add your description here
Author: jianfei2024
Author-email: jianfei2024 <yangjianfei177@gmail.com>
Requires-Dist: mcp[cli]>=1.13.1
Requires-Python: >=3.12
